LICENSE
MANIFEST.in
README.md
setup.py
apimaticcicddemov10/__init__.py
apimaticcicddemov10/api_helper.py
apimaticcicddemov10/apimaticcicddemov_10_client.py
apimaticcicddemov10/configuration.py
apimaticcicddemov10/decorators.py
apimaticcicddemov10.egg-info/PKG-INFO
apimaticcicddemov10.egg-info/SOURCES.txt
apimaticcicddemov10.egg-info/dependency_links.txt
apimaticcicddemov10.egg-info/requires.txt
apimaticcicddemov10.egg-info/top_level.txt
apimaticcicddemov10/controllers/__init__.py
apimaticcicddemov10/controllers/base_controller.py
apimaticcicddemov10/controllers/simple_calculator_controller.py
apimaticcicddemov10/exceptions/__init__.py
apimaticcicddemov10/exceptions/api_exception.py
apimaticcicddemov10/http/__init__.py
apimaticcicddemov10/http/http_call_back.py
apimaticcicddemov10/http/http_client.py
apimaticcicddemov10/http/http_context.py
apimaticcicddemov10/http/http_method_enum.py
apimaticcicddemov10/http/http_request.py
apimaticcicddemov10/http/http_response.py
apimaticcicddemov10/http/requests_client.py
apimaticcicddemov10/models/__init__.py
apimaticcicddemov10/models/operation_type_enum.py
tests/__init__.py
tests/http_response_catcher.py
tests/test_helper.py
tests/controllers/__init__.py
tests/controllers/controller_test_base.py
tests/controllers/test_simple_calculator_controller.py