Metadata-Version: 1.0
Name: apimaticcicddemov10
Version: 1.0.4
Summary: Simple calculator API hosted on APIMATIC
Home-page: https://apimatic.io
Author: APIMatic SDK Generator
Author-email: support@apimatic.io
License: UNKNOWN
Platform: UNKNOWN
